LICENSE.txt
MANIFEST.in
README.md
setup.cfg
setup.py
pdfsBlankDetection/__init__.py
pdfsBlankDetection/pdf_result_tables.pyd
pdfsBlankDetection/pdfsBlankDetection.pyd
pdfsBlankDetection/pdfsBlankDetectionF.pyd
pdfsBlankDetection/pdfsBlankDetectionResultUi.pyd
pdfsBlankDetection/pdfsBlankDetectionUi.pyd
pdfsBlankDetection.egg-info/PKG-INFO
pdfsBlankDetection.egg-info/SOURCES.txt
pdfsBlankDetection.egg-info/dependency_links.txt
pdfsBlankDetection.egg-info/top_level.txt