Metadata-Version: 2.1
Name: pdfsBlankDetection
Version: 0.2.2
Summary: 检测疑似空白页的代码
Home-page: https://alidocs.dingtalk.com/i/p/4oJRz0VRJyvmLZMydy0mV7WvjQn7MG89
Author: zhaojianhua
Author-email: 17891967090@163.com
Classifier: Programming Language :: Python
Requires-Python: >=3.8
License-File: LICENSE.txt
